ustack_tornado_shutdown/__init__.py
ustack_tornado_shutdown/graceful_shutdown.py
ustack_tornado_shutdown/py.typed
ustack_tornado_shutdown-1.0.0.dist-info/LICENSE
ustack_tornado_shutdown-1.0.0.dist-info/WHEEL
ustack_tornado_shutdown-1.0.0.dist-info/METADATA
ustack_tornado_shutdown-1.0.0.dist-info/RECORD
