Metadata-Version: 2.1
Name: ustack-tornado-shutdown
Version: 1.0.0
Summary: Library for gracefully terminating a Tornado server on SIGTERM
License: MIT
Author: uStudio Developers
Author-email: dev@ustudio.com
Requires-Python: >=3.9,<4.0
Classifier: License :: OSI Approved :: MIT License
Classifier: Programming Language :: Python :: 3
Classifier: Programming Language :: Python :: 3.10
Classifier: Programming Language :: Python :: 3.9
